{
    "_id": "23GpILO1Ds6US3Fu",
    "folder": "CdXuDn0XHKdh7M6j",
    "img": "systems/sf2e/icons/default-icons/feats-sf2e.webp",
    "name": "Entangling Mycelium",
    "system": {
        "actionType": {
            "value": "action"
        },
        "actions": {
            "value": 1
        },
        "category": "ancestry",
        "description": {
            "value": "<p>You allow your spores to spread. The ground in your square becomes difficult terrain for all non-fungi creatures for 1 minute. If you're already in a square affected by Entangling Mycelium, the fungus spreads and all non-diagonal adjacent squares become difficult terrain for 1 minute.</p>"
        },
        "level": {
            "value": 5
        },
        "prerequisites": {
            "value": []
        },
        "publication": {
            "license": "ORC",
            "remaster": true,
            "title": "Starfinder Galactic Ancestries"
        },
        "rules": [],
        "subfeatures": {
            "proficiencies": {},
            "senses": {},
            "suppressedFeatures": []
        },
        "traits": {
            "rarity": "common",
            "value": [
                "entu-colony"
            ]
        }
    },
    "type": "feat"
}
