{
    "_id": "xdJTtTALCunhMk41",
    "folder": "CdXuDn0XHKdh7M6j",
    "img": "systems/sf2e/icons/default-icons/feats-sf2e.webp",
    "name": "Symbiotic Summon",
    "system": {
        "actionType": {
            "value": "free"
        },
        "actions": {
            "value": null
        },
        "category": "ancestry",
        "description": {
            "value": "<p>You can instantly merge with a creature you summon. If the next action you use is to Cast a Spell that summons a minion, you merge with the minion instead of summoning them. This works like animal form, except your form's Size, Speeds, AC, senses, attacks, and Athletics modifiers are identical to the summoned creature (you don't gain temporary Hit Points). If you're reduced to 0 Hit Points while merged with your summoned minion, the effect ends, and you return to your normal self with half as many Hit Points as you originally had when you first merged with your summoned minion.</p>"
        },
        "level": {
            "value": 5
        },
        "prerequisites": {
            "value": [
                {
                    "value": "Hostless Entu heritage"
                }
            ]
        },
        "publication": {
            "license": "ORC",
            "remaster": true,
            "title": "Starfinder Galactic Ancestries"
        },
        "rules": [],
        "subfeatures": {
            "proficiencies": {},
            "senses": {},
            "suppressedFeatures": []
        },
        "traits": {
            "rarity": "common",
            "value": [
                "concentrate",
                "entu-colony",
                "spellshape"
            ]
        }
    },
    "type": "feat"
}
