{
    "_id": "EuZSh1KKHHjSdZ1A",
    "folder": "6xguUrxLFWX6owxI",
    "img": "systems/sf2e/icons/default-icons/feats-sf2e.webp",
    "name": "Hidden Talent",
    "system": {
        "actionType": {
            "value": "passive"
        },
        "actions": {
            "value": null
        },
        "category": "ancestry",
        "description": {
            "value": "<p>You have niche expertise or esoteric training that you often fall back on when you find yourself in a rut. You gain the @UUID[Compendium.sf2e.actions.Item.One Up] reaction.</p>"
        },
        "level": {
            "value": 9
        },
        "prerequisites": {
            "value": []
        },
        "publication": {
            "license": "ORC",
            "remaster": true,
            "title": "Starfinder Galactic Ancestries"
        },
        "rules": [
            {
                "key": "GrantItem",
                "uuid": "Compendium.sf2e.actions.Item.One Up"
            }
        ],
        "subfeatures": {
            "proficiencies": {},
            "senses": {},
            "suppressedFeatures": []
        },
        "traits": {
            "rarity": "common",
            "value": [
                "urog"
            ]
        }
    },
    "type": "feat"
}
