{
    "_id": "0MQ2lpW2IhPVXczh",
    "folder": "IGZeBKeH3esdU74F",
    "img": "systems/sf2e/icons/default-icons/heritage.svg",
    "name": "Mindstatic Orocoran",
    "system": {
        "ancestry": {
            "name": "Orocoran",
            "slug": "orocoran",
            "uuid": "Compendium.sf2e.ancestries.Item.6BG5tO0g9kCFfTym"
        },
        "description": {
            "value": "<p>Your mind releases a steady psychic static that you can instinctively wield to scramble incoming mental signals, shielding you from mind control and psychic attacks. You gain the @UUID[Compendium.sf2e.actions.Item.Static Shield] reaction.</p>"
        },
        "publication": {
            "license": "ORC",
            "remaster": true,
            "title": "Starfinder Galactic Ancestries"
        },
        "rules": [
            {
                "key": "GrantItem",
                "uuid": "Compendium.sf2e.actions.Item.Static Shield"
            }
        ],
        "traits": {
            "rarity": "common",
            "value": []
        }
    },
    "type": "heritage"
}
