{
    "_id": "JnpK0Ka0vj91Wilr",
    "folder": "cX8TUsVTscl6CU2W",
    "img": "systems/sf2e/icons/default-icons/feats-sf2e.webp",
    "name": "Rush of Adrenaline",
    "system": {
        "actionType": {
            "value": "free"
        },
        "actions": {
            "value": null
        },
        "category": "ancestry",
        "description": {
            "value": "<p><strong>Frequency</strong> once per hour</p>\n<p><strong>Trigger</strong> You succeed at a saving throw.</p><hr /><p>You know that nothing in life is guaranteed, and you feel invigorated every time you overcome the challenges life throws at you. You're certain that you'll live to see another day. You gain a number of temporary Hit Points equal to your level that last for 1 minute. If you critically succeeded on the triggering save, you are also @UUID[Compendium.sf2e.conditions.Item.Quickened] during your next turn and can use your extra action only to Stride or Strike.</p>"
        },
        "frequency": {
            "max": 1,
            "per": "PT1H"
        },
        "level": {
            "value": 17
        },
        "prerequisites": {
            "value": []
        },
        "publication": {
            "license": "ORC",
            "remaster": true,
            "title": "Starfinder Galactic Ancestries"
        },
        "rules": [],
        "subfeatures": {
            "proficiencies": {},
            "senses": {},
            "suppressedFeatures": []
        },
        "traits": {
            "rarity": "common",
            "value": [
                "orocoran"
            ]
        }
    },
    "type": "feat"
}
