{
    "_id": "MxDwiosYgMNaANZC",
    "folder": "22yFNd1x6LziQ5HL",
    "img": "systems/sf2e/icons/default-icons/feats-sf2e.webp",
    "name": "Exclusively Quadrupedal",
    "system": {
        "actionType": {
            "value": "passive"
        },
        "actions": {
            "value": null
        },
        "category": "ancestry",
        "description": {
            "value": "<p>You use your middle arms as feet so much that you've lost the ability to use them as arms. You lose the @UUID[Compendium.sf2e.actions.Item.Change Posture] action, and you can no longer be in bipedal posture. Your land Speed increases to 40 feet. You gain the @UUID[Compendium.sf2e.feats.Item.Solid Stance] feat. If you already had the Solid Stance feat, you can retrain that feat to another ancestry feat when you select this feat.</p>"
        },
        "level": {
            "value": 13
        },
        "prerequisites": {
            "value": [
                {
                    "value": "Consistently Quadrupedal"
                }
            ]
        },
        "publication": {
            "license": "ORC",
            "remaster": true,
            "title": "Starfinder Galactic Ancestries"
        },
        "rules": [
            {
                "allowDuplicate": false,
                "key": "GrantItem",
                "uuid": "Compendium.sf2e.feats.Item.Solid Stance"
            },
            {
                "key": "FlatModifier",
                "selector": [
                    "land-speed"
                ],
                "slug": "consistently-quadrupedal-speed",
                "value": 5
            }
        ],
        "subfeatures": {
            "proficiencies": {},
            "senses": {},
            "suppressedFeatures": []
        },
        "traits": {
            "rarity": "common",
            "value": [
                "izalguun"
            ]
        }
    },
    "type": "feat"
}
