{
    "_id": "pMWCzpcGTF947pgY",
    "folder": "7ZGm7HME6bLXHyKC",
    "img": "systems/sf2e/icons/default-icons/feats-sf2e.webp",
    "name": "Fortune Favors the Bold",
    "system": {
        "actionType": {
            "value": "action"
        },
        "actions": {
            "value": 1
        },
        "category": "ancestry",
        "description": {
            "value": "<p><strong>Requirements</strong> Your last action was a Strike that critically hit a Large or larger creature.</p><hr /><p>People think you're just lucky, but in truth, you're simply always prepared to seize an opportunity when it presents itself, even in the face of seemingly impossible odds. Automatically [[/act shove]] the target 10 feet away from you. The target is @UUID[Compendium.sf2e.conditions.Item.Off-Guard] until the end of your current turn.</p>"
        },
        "level": {
            "value": 9
        },
        "prerequisites": {
            "value": []
        },
        "publication": {
            "license": "ORC",
            "remaster": true,
            "title": "Starfinder Galactic Ancestries"
        },
        "rules": [],
        "subfeatures": {
            "proficiencies": {},
            "senses": {},
            "suppressedFeatures": []
        },
        "traits": {
            "rarity": "common",
            "value": [
                "halfling"
            ]
        }
    },
    "type": "feat"
}
