{
    "_id": "n05RMubFfXt0nAhO",
    "folder": "SUr2V7rryBTohlSG",
    "img": "systems/sf2e/icons/default-icons/heritage.svg",
    "name": "Voidcore Android",
    "system": {
        "ancestry": {
            "name": "Android",
            "slug": "android",
            "uuid": "Compendium.sf2e.ancestries.Item.GfLwE884NoRC7cRi"
        },
        "description": {
            "value": "<p>Your body is powered by a voidcore: an ancient marvel of technology with shrouded origins, older than most things in the galaxy. The first voidcores were constructed to power far larger equipment, but eventually they found their way into the heart of androids as an operational enhancement to existing cores. Today, voidcore androids are created by harnessing entropy through a ritual of corruption that calls on the Void. This influx of entropy reverses the energy state of the android, inverting the soul itself in the process. You're a voidcore android, with black, blue, or violet energy surging through your circuitry.</p>\n<p>You have void healing, which means you're damaged by vitality damage and not healed by healing vitality effects, and you don't take void damage and are healed by void effects that heal undead. You gain darkvision.</p>"
        },
        "publication": {
            "license": "ORC",
            "remaster": true,
            "title": "Starfinder Galactic Ancestries"
        },
        "rules": [
            {
                "key": "ActiveEffectLike",
                "mode": "override",
                "path": "system.attributes.hp.negativeHealing",
                "value": true
            },
            {
                "key": "Sense",
                "selector": "darkvision"
            }
        ],
        "traits": {
            "rarity": "common",
            "value": []
        }
    },
    "type": "heritage"
}
