{
    "_id": "OTCKbbMZ0p8gvbqb",
    "folder": "t83Pstr2fTxtylhH",
    "img": "systems/sf2e/icons/default-icons/feats-sf2e.webp",
    "name": "Patient Waiter",
    "system": {
        "actionType": {
            "value": "passive"
        },
        "actions": {
            "value": null
        },
        "category": "ancestry",
        "description": {
            "value": "<p>In traditional processes, a large part of an individual's life is spent waiting; you add value by reducing the amount of time wasted by waiting. You gain a +2 circumstance bonus to initiative rolls.</p>"
        },
        "level": {
            "value": 5
        },
        "prerequisites": {
            "value": []
        },
        "publication": {
            "license": "ORC",
            "remaster": true,
            "title": "Starfinder Galactic Ancestries"
        },
        "rules": [
            {
                "key": "FlatModifier",
                "removeAfterRoll": [
                    "check:type:initiative"
                ],
                "selector": "initiative",
                "slug": "patient-waiver-bonus",
                "type": "circumstance",
                "value": 2
            }
        ],
        "subfeatures": {
            "proficiencies": {},
            "senses": {},
            "suppressedFeatures": []
        },
        "traits": {
            "rarity": "common",
            "value": [
                "urog"
            ]
        }
    },
    "type": "feat"
}
